minimization/__init__.py
minimization/_version.py
minimization/minimizer.py
minimization/tests/__init__.py
minimization/tests/test_common.py
minimization/tests/test_minimizer.py
ai_minimization_toolkit-0.0.1.dist-info/LICENSE
ai_minimization_toolkit-0.0.1.dist-info/METADATA
ai_minimization_toolkit-0.0.1.dist-info/WHEEL
ai_minimization_toolkit-0.0.1.dist-info/top_level.txt
ai_minimization_toolkit-0.0.1.dist-info/RECORD
